{"Certificate Requirements": ["Minimum 12 credits", "Minimum grade of 'C' in courses applied to the certificate"], "Required Courses (6 credits)": {"Complete the following:": ["IS 325 - Introduction to Management Science (3)", "IS 425 - Decision Support Systems (3)"]}, "Electives (6 credits)": {"Complete 6 credits from the following:": ["IS 427 - Introduction to Artificial Intelligence: Concepts and Applications (3)", "IS 428 - Data Mining Techniques and Applications (3)", "IS 438 - Project Management (3)"]}}