{"Certificate Requirements": ["Minimum 17 credits, including a minimum of 3 courses completed in residence at UMBC", "Minimum grade of 'B' in courses applied to the certificate", "Not open to students pursuing a Modern Languages, Linguistics & Intercultural Communication major or minor"], "German Language (11 credits)": {"Complete the following:": ["GERM 201 - Intermediate German I (4)", "GERM 202 - Gateway to Advanced German Studies (4)", "GERM 301 - Advanced German Studies I (3)"]}, "Electives (6 credits)": {"Complete 6 credits from the following:": ["Additional upper-level GERM courses", "MLL 214 - The New German Cinema (3)", "MLL 216 - Classics in German Cinema (3)", "MLL 261 - German Ethnic and Cultural Identity (3)", "MLL 332 - Topics in German Culture (3)"]}}